{
	"class" : {
		"byteAlignment" : " 11/28/2016 11:42:15",
		"fieldsDesc" : " 11/28/2016 11:42:15" },
	"instance" : {
		"boundary" : " 11/28/2016 11:42:15",
		"finalCommitId" : " 11/28/2016 11:42:15",
		"finalSignature" : " 11/28/2016 11:42:15",
		"finalStartLineNumber" : " 11/28/2016 11:42:15",
		"numberOfLines" : " 11/28/2016 11:42:15",
		"originalCommitId" : " 11/28/2016 11:42:15",
		"originalPath" : " 11/28/2016 11:42:15",
		"originalSignature" : " 11/28/2016 11:42:15",
		"originalStartLineNumber" : " 11/28/2016 11:42:15",
		"prim_boundary" : " 11/28/2016 11:42:15",
		"prim_boundary:" : " 11/28/2016 11:42:15",
		"prim_final_commit_id" : " 11/28/2016 11:42:15",
		"prim_final_commit_id:" : " 11/28/2016 11:42:15",
		"prim_final_signature" : " 11/28/2016 11:42:15",
		"prim_final_signature:" : " 11/28/2016 11:42:15",
		"prim_final_start_line_number" : " 11/28/2016 11:42:15",
		"prim_final_start_line_number:" : " 11/28/2016 11:42:15",
		"prim_lines_in_hunk" : " 11/28/2016 11:42:15",
		"prim_lines_in_hunk:" : " 11/28/2016 11:42:15",
		"prim_orig_commit_id" : " 11/28/2016 11:42:15",
		"prim_orig_commit_id:" : " 11/28/2016 11:42:15",
		"prim_orig_path" : " 11/28/2016 11:42:15",
		"prim_orig_path:" : " 11/28/2016 11:42:15",
		"prim_orig_signature" : " 11/28/2016 11:42:15",
		"prim_orig_signature:" : " 11/28/2016 11:42:15",
		"prim_orig_start_line_number" : " 11/28/2016 11:42:15",
		"prim_orig_start_line_number:" : " 11/28/2016 11:42:15" } }
